.hgignore
.hgtags
CHANGES.txt
LICENSE.txt
README.txt
bootstrap.py
buildout.cfg
setup.py
js/__init__.py
js.jquery_tools.egg-info/PKG-INFO
js.jquery_tools.egg-info/SOURCES.txt
js.jquery_tools.egg-info/dependency_links.txt
js.jquery_tools.egg-info/entry_points.txt
js.jquery_tools.egg-info/namespace_packages.txt
js.jquery_tools.egg-info/not-zip-safe
js.jquery_tools.egg-info/requires.txt
js.jquery_tools.egg-info/top_level.txt
js/jquery_tools/__init__.py
js/jquery_tools/test_jquery_tools.txt
js/jquery_tools/resources/README.txt
js/jquery_tools/resources/jquery.tools.min.js