Metadata-Version: 1.0
Name: js.jquery-tools
Version: 1.2.7
Summary: Fanstatic packaging of jQueryTools
Home-page: UNKNOWN
Author: Fanstatic Developers
Author-email: fanstatic@googlegroups.com
License: BSD
Platform: UNKNOWN
